doover_cli/__init__.py
doover_cli/agent.py
doover_cli/apps.py
doover_cli/channel.py
doover_cli/config_schema.py
doover_cli/dda_logs.py
doover_cli/doover_config.py
doover_cli/grpc.py
doover_cli/login.py
doover_cli/report.py
doover_cli/simulator.py
doover_cli/tunnel.py
doover_cli/utils/__init__.py
doover_cli/utils/api.py
doover_cli/utils/apps.py
doover_cli/utils/context.py
doover_cli/utils/decorators.py
doover_cli/utils/errors.py
doover_cli/utils/formatters.py
doover_cli/utils/misc.py
doover_cli/utils/parsers.py
doover_cli/utils/prompt.py
doover_cli/utils/shell_commands.py
doover_cli/utils/state.py
doover_cli-0.1.8.dist-info/METADATA
doover_cli-0.1.8.dist-info/WHEEL
doover_cli-0.1.8.dist-info/entry_points.txt
doover_cli-0.1.8.dist-info/licenses/LICENSE
doover_cli-0.1.8.dist-info/RECORD
