Metadata-Version: 2.4
Name: doover-cli
Version: 0.1.8
Summary: CLI for Doover
License-File: LICENSE
Requires-Python: >=3.11
Requires-Dist: click-prompt>=0.6.3
Requires-Dist: click<8.2.0
Requires-Dist: docker>=7.1.0
Requires-Dist: jsf>=0.11.2
Requires-Dist: paramiko>=3.5.1
Requires-Dist: pydoover>=0.4.11
Requires-Dist: pytz>=2025.2
Requires-Dist: questionary>=1.10.0
Requires-Dist: requests>=2.32.3
Requires-Dist: typer==0.15.1
Requires-Dist: tzlocal>=5.3.1
Requires-Dist: xlsxwriter>=3.2.3
